README.md
setup.py
plantuml_wrapper/__init__.py
plantuml_wrapper/__main__.py
plantuml_wrapper.egg-info/PKG-INFO
plantuml_wrapper.egg-info/SOURCES.txt
plantuml_wrapper.egg-info/dependency_links.txt
plantuml_wrapper.egg-info/entry_points.txt
plantuml_wrapper.egg-info/top_level.txt