Metadata-Version: 1.1
Name: plantuml-wrapper
Version: 0.0.3
Summary: os independent wrapper around plantuml.jar
Home-page: https://github.com/wingechr/plantuml-wrapper
Author: Christian Winger
Author-email: c@wingechr.de
License: UNKNOWN
Platform: UNKNOWN
Classifier: Programming Language :: Python :: 3.3
Classifier: Programming Language :: Python :: 3.4
Classifier: Programming Language :: Python :: 3.5
Classifier: Programming Language :: Python :: 3.6
Classifier: Programming Language :: Python :: 3.7
Classifier: Operating System :: OS Independent
